predeldomain/__init__.py
predeldomain/__main__.py
predeldomain/app/entry.py
predeldomain/provider/provider.py
predeldomain/provider/provider_cn.py
predeldomain/provider/provider_top.py
predeldomain/utils/enum.py
predeldomain-0.2.0.dist-info/METADATA
predeldomain-0.2.0.dist-info/WHEEL
predeldomain-0.2.0.dist-info/entry_points.txt
predeldomain-0.2.0.dist-info/licenses/LICENSE
predeldomain-0.2.0.dist-info/RECORD
