Metadata-Version: 2.4
Name: predeldomain
Version: 0.2.0
Summary: 预删除域名查询
Project-URL: Homepage, https://git.jetsung.com/idev/predeldomain
Project-URL: Documentation, https://framagit.org/idev/predeldomain
Project-URL: Repository, https://framagit.org/idev/predeldomain.git
Author-email: Jetsung Chan <jetsungchan@gmail.com>
License: Apache-2.0
License-File: LICENSE
Keywords: domain
Classifier: Development Status :: 4 - Beta
Classifier: Environment :: Console
Classifier: Environment :: Web Environment
Classifier: Intended Audience :: Developers
Classifier: License :: OSI Approved :: Apache Software License
Classifier: Natural Language :: Chinese (Simplified)
Classifier: Operating System :: OS Independent
Classifier: Programming Language :: Python
Classifier: Programming Language :: Python :: 3
Classifier: Programming Language :: Python :: 3 :: Only
Classifier: Programming Language :: Python :: 3.10
Classifier: Programming Language :: Python :: 3.11
Classifier: Programming Language :: Python :: 3.12
Classifier: Programming Language :: Python :: Implementation :: CPython
Classifier: Topic :: Communications :: Email
Classifier: Topic :: Software Development :: Libraries
Requires-Python: >=3.10
Requires-Dist: ipush>=0.6.0
Requires-Dist: pre-commit>=4.0.1
Requires-Dist: ruff>=0.8.3
Requires-Dist: whois>=1.20240129.2
